[
  {
    "id": "guardian_dead",
    "aspects": [
      {
        "name": "guardian",
        "level": 0
      }
    ],
    "overcomes": ["edge", "winter", null]
  },
  {
    "id": "guardian_long",
    "aspects": [
      {
        "name": "guardian",
        "level": 0
      }
    ],
    "overcomes": ["grail", "moth", null]
  },
  {
    "id": "guardian_monks",
    "aspects": [
      {
        "name": "guardian",
        "level": 0
      }
    ],
    "overcomes": ["edge", "moth", null]
  },
  {
    "id": "guardian_serpent",
    "aspects": [
      {
        "name": "guardian",
        "level": 0
      }
    ],
    "overcomes": ["edge", "knock", null]
  },
  {
    "id": "guardian_soucouyants",
    "aspects": [
      {
        "name": "guardian",
        "level": 0
      }
    ],
    "overcomes": ["lantern", "moth", null]
  },
  {
    "id": "guardian_watchers",
    "aspects": [
      {
        "name": "guardian",
        "level": 0
      }
    ],
    "overcomes": ["edge", "grail", "moth"]
  },
  {
    "id": "seal_hiddendoor",
    "aspects": [
      {
        "name": "seal",
        "level": 0
      }
    ],
    "overcomes": ["knock", "lantern", null]
  },
  {
    "id": "seal_wardeddoor",
    "aspects": [
      {
        "name": "seal",
        "level": 0
      }
    ],
    "overcomes": ["forge", "knock", null]
  },
  {
    "id": "peril_desert",
    "aspects": [
      {
        "name": "peril",
        "level": 0
      }
    ],
    "overcomes": ["forge", "grail", null]
  },
  {
    "id": "peril_forest",
    "aspects": [
      {
        "name": "peril",
        "level": 0
      }
    ],
    "overcomes": ["forge", "moth", null]
  },
  {
    "id": "peril_mountains",
    "aspects": [
      {
        "name": "peril",
        "level": 0
      }
    ],
    "overcomes": ["forge", "winter", null]
  },
  {
    "id": "peril_sea",
    "aspects": [
      {
        "name": "peril",
        "level": 0
      }
    ],
    "overcomes": ["forge", "heart", null]
  },
  {
    "id": "peril_treacherousground",
    "aspects": [
      {
        "name": "peril",
        "level": 0
      }
    ],
    "overcomes": ["forge", "lantern", null]
  },
  {
    "id": "curse_affliction",
    "aspects": [
      {
        "name": "curse",
        "level": 0
      }
    ],
    "overcomes": ["grail", "heart", null]
  },
  {
    "id": "curse_dread",
    "aspects": [
      {
        "name": "curse",
        "level": 0
      }
    ],
    "overcomes": ["heart", "lantern", null]
  },
  {
    "id": "curse_nowhere",
    "aspects": [
      {
        "name": "curse",
        "level": 0
      }
    ],
    "overcomes": ["lantern", "moth", null]
  },
  {
    "id": "curse_visions",
    "aspects": [
      {
        "name": "curse",
        "level": 0
      }
    ],
    "overcomes": ["heart", "winter", null]
  }
]
